moviedex/__init__.py
moviedex/film_client.py
moviedex/film_config.py
moviedex/schemas/__init__.py
moviedex/schemas/schemas.py
moviedex-0.0.2.dist-info/METADATA
moviedex-0.0.2.dist-info/WHEEL
moviedex-0.0.2.dist-info/top_level.txt
moviedex-0.0.2.dist-info/RECORD
